voltcraft/__init__.py
voltcraft/__main__.py
voltcraft/_version.py
voltcraft/pps.py
voltcraft-1.7.1.dist-info/licenses/LICENSE.md
voltcraft-1.7.1.dist-info/METADATA
voltcraft-1.7.1.dist-info/WHEEL
voltcraft-1.7.1.dist-info/top_level.txt
voltcraft-1.7.1.dist-info/RECORD
