Metadata-Version: 2.4
Name: voltcraft
Version: 1.7.1
Summary: library for controlling Voltcraft PPS power supplies
Author-email: Andreas Poehlmann <andreas@poehlmann.io>
License: Copyright (C) 2012-2020 Andreas Poehlmann <andreas@poehlmann.io>
Project-URL: Homepage, https://github.com/ap--/voltcraft.git
Project-URL: Download, https://github.com/ap--/voltcraft
Project-URL: Source, https://github.com/ap--/voltcraft
Classifier: Development Status :: 5 - Production/Stable
Classifier: Intended Audience :: Science/Research
Classifier: License :: OSI Approved :: MIT License
Classifier: Programming Language :: Python
Classifier: Programming Language :: Python :: 3
Classifier: Topic :: Scientific/Engineering
Classifier: Topic :: Utilities
Classifier: Operating System :: Microsoft :: Windows
Classifier: Operating System :: POSIX
Classifier: Operating System :: Unix
Classifier: Operating System :: MacOS
Requires-Python: >=3.8
License-File: LICENSE.md
Requires-Dist: pyserial
Dynamic: license-file
